helperdb/__init__.py
helperdb/helperdb.py
tests/__init__.py
tests/test1.py
tests/test_database.py
helperdb-0.0.1.dist-info/LICENSE
helperdb-0.0.1.dist-info/METADATA
helperdb-0.0.1.dist-info/WHEEL
helperdb-0.0.1.dist-info/top_level.txt
helperdb-0.0.1.dist-info/RECORD
