Metadata-Version: 2.1
Name: helperdb
Version: 0.0.1
Summary: A database system for discord bots
License-File: LICENSE
Requires-Dist: aiosqlite
